db/__init__.py
py_yaml_fixtures/__init__.py
py_yaml_fixtures/apps.py
py_yaml_fixtures/bundle.py
py_yaml_fixtures/commands.py
py_yaml_fixtures/fixtures_loader.py
py_yaml_fixtures/hooks.py
py_yaml_fixtures/types.py
py_yaml_fixtures/utils.py
py_yaml_fixtures/factories/__init__.py
py_yaml_fixtures/factories/django.py
py_yaml_fixtures/factories/factory_interface.py
py_yaml_fixtures/factories/sqlalchemy.py
py_yaml_fixtures/flask/__init__.py
py_yaml_fixtures/flask/cli.py
py_yaml_fixtures/management/__init__.py
py_yaml_fixtures/management/commands/__init__.py
py_yaml_fixtures/management/commands/import_fixtures.py
py_yaml_fixtures-0.6.2.dist-info/LICENSE
py_yaml_fixtures-0.6.2.dist-info/METADATA
py_yaml_fixtures-0.6.2.dist-info/WHEEL
py_yaml_fixtures-0.6.2.dist-info/top_level.txt
py_yaml_fixtures-0.6.2.dist-info/RECORD
