Metadata-Version: 2.1
Name: py-yaml-fixtures
Version: 0.6.2
Summary: Load Django and SQLAlchemy database fixtures from Jinja-templated YAML files
Home-page: https://github.com/briancappello/py-yaml-fixtures
Author: Brian Cappello
License: MIT
Classifier: Development Status :: 4 - Beta
Classifier: Intended Audience :: Developers
Classifier: License :: OSI Approved :: MIT License
Classifier: Programming Language :: Python :: 3
Classifier: Programming Language :: Python :: 3.5
Classifier: Programming Language :: Python :: 3.6
Requires-Python: >=3.5
License-File: LICENSE
Requires-Dist: faker >=1.0.7
Requires-Dist: jinja2 >=2.10.1
Requires-Dist: networkx >=2.3
Requires-Dist: python-dateutil >=2.8.0
Requires-Dist: PyYAML >=5.1
Provides-Extra: dev
Requires-Dist: django >=2.1 ; extra == 'dev'
Requires-Dist: flask >=1.0 ; extra == 'dev'
Requires-Dist: pytest ; extra == 'dev'
Requires-Dist: sqlalchemy >=1.0 ; extra == 'dev'
Provides-Extra: django
Requires-Dist: django >=2.0 ; extra == 'django'
Provides-Extra: docs
Requires-Dist: django >=2.1 ; extra == 'docs'
Requires-Dist: flask >=1.0 ; extra == 'docs'
Requires-Dist: m2r ; extra == 'docs'
Requires-Dist: sphinx ; extra == 'docs'
Requires-Dist: sphinx-autobuild ; extra == 'docs'
Requires-Dist: sphinx-rtd-theme ; extra == 'docs'
Requires-Dist: sqlalchemy >=1.0 ; extra == 'docs'
Provides-Extra: flask-sqlalchemy
Requires-Dist: click >=6.7 ; extra == 'flask-sqlalchemy'
Requires-Dist: flask >=1.0 ; extra == 'flask-sqlalchemy'
Requires-Dist: flask-sqlalchemy >=2.2 ; extra == 'flask-sqlalchemy'
Provides-Extra: flask-unchained
Requires-Dist: flask-migrate >=2.2.1 ; extra == 'flask-unchained'
Requires-Dist: flask-unchained >=0.8.0 ; extra == 'flask-unchained'
Requires-Dist: flask-sqlalchemy-unchained >=0.7.3 ; extra == 'flask-unchained'
Requires-Dist: sqlalchemy-unchained >=0.7.6 ; extra == 'flask-unchained'
Provides-Extra: sqlalchemy
Requires-Dist: sqlalchemy >=1.0 ; extra == 'sqlalchemy'
